testrail_api_reporter/.flake8
testrail_api_reporter/.gitignore
testrail_api_reporter/.pylintrc
testrail_api_reporter/CODE_OF_CONDUCT.md
testrail_api_reporter/CONTRIBUTING.md
testrail_api_reporter/LICENSE
testrail_api_reporter/README.md
testrail_api_reporter/SECURITY.md
testrail_api_reporter/__init__.py
testrail_api_reporter/mypy.ini
testrail_api_reporter/pull_request_template.md
testrail_api_reporter/pyproject.toml
testrail_api_reporter/pytest.ini
testrail_api_reporter/requirements.txt
testrail_api_reporter/.github/dependabot.yml
testrail_api_reporter/.github/workflows/linters.yml
testrail_api_reporter/.github/workflows/master_linters.yml
testrail_api_reporter/.github/workflows/master_tests.yml
testrail_api_reporter/.github/workflows/tests.yml
testrail_api_reporter/screenshots/tr_at_run_detailed_report.png
testrail_api_reporter/screenshots/tr_at_run_report.png
testrail_api_reporter/screenshots/tr_confluence_report.png
testrail_api_reporter/screenshots/tr_email_report.png
testrail_api_reporter/screenshots/tr_gdrive_backup.png
testrail_api_reporter/screenshots/tr_slack_report.png
testrail_api_reporter/testrail_api_reporter/__init__.py
testrail_api_reporter/testrail_api_reporter/engines/__init__.py
testrail_api_reporter/testrail_api_reporter/engines/at_coverage_reporter.py
testrail_api_reporter/testrail_api_reporter/engines/case_backup.py
testrail_api_reporter/testrail_api_reporter/engines/plotly_reporter.py
testrail_api_reporter/testrail_api_reporter/engines/results_reporter.py
testrail_api_reporter/testrail_api_reporter/publishers/__init__.py
testrail_api_reporter/testrail_api_reporter/publishers/confluence_sender.py
testrail_api_reporter/testrail_api_reporter/publishers/email_sender.py
testrail_api_reporter/testrail_api_reporter/publishers/gdrive_uploader.py
testrail_api_reporter/testrail_api_reporter/publishers/slack_sender.py
testrail_api_reporter/testrail_api_reporter/utils/__init__.py
testrail_api_reporter/testrail_api_reporter/utils/case_stat.py
testrail_api_reporter-1.4.13.dist-info/METADATA
testrail_api_reporter-1.4.13.dist-info/WHEEL
testrail_api_reporter-1.4.13.dist-info/licenses/LICENSE
testrail_api_reporter-1.4.13.dist-info/RECORD
