Metadata-Version: 2.4
Name: testrail_api_reporter
Version: 1.4.13
Summary: TestRail API reporter tools
Project-URL: Homepage, https://github.com/wwakabobik/testrail_api_reporter
Project-URL: Bug Tracker, https://github.com/wwakabobik/testrail_api_reporter/issues
Project-URL: Contribution Guide, https://github.com/wwakabobik/testrail_api_reporter/blob/main/CONTRIBUTING.md
Project-URL: Donations, https://www.donationalerts.com/r/rocketsciencegeek
Author-email: Iliya Vereshchagin <i.vereshchagin@gmail.com>
Maintainer-email: Iliya Vereshchagin <i.vereshchagin@gmail.com>
License: MIT License
License-File: LICENSE
Keywords: api,automation,automation-testing,chart,confluence,email,google-drive,pytest,pytest-report,qa,reporter,reports,slack,testing,testing-tools,testrail,testrail-api,testrail-python,testrail-reporting
Classifier: Intended Audience :: Developers
Classifier: Intended Audience :: Information Technology
Classifier: License :: OSI Approved :: MIT License
Classifier: Operating System :: OS Independent
Classifier: Programming Language :: Python :: 3.8
Classifier: Programming Language :: Python :: 3.9
Classifier: Programming Language :: Python :: 3.10
Classifier: Programming Language :: Python :: 3.11
Classifier: Programming Language :: Python :: 3.12
Classifier: Programming Language :: Python :: 3.13
Classifier: Topic :: Software Development :: Libraries :: Python Modules
Classifier: Topic :: Software Development :: Testing
Requires-Python: >=3.8
Requires-Dist: atlassian-python-api
Requires-Dist: beautifulsoup4
Requires-Dist: google-api-python-client
Requires-Dist: google-auth-httplib2
Requires-Dist: google-auth-oauthlib
Requires-Dist: httplib2
Requires-Dist: kaleido
Requires-Dist: oauth2client
Requires-Dist: plotly
Requires-Dist: psutil
Requires-Dist: requests
Requires-Dist: testrail-api
Requires-Dist: xmltodict
